lion/__init__.py
lion/algorithms.py
lion/angle_graph.py
lion/fast_shortest_path.py
lion/ksp.py
lion/tests/__init__.py
lion/tests/run_example.py
lion/tests/test_angle_graph.py
lion/tests/test_api.py
lion/tests/test_ksp.py
lion/tests/test_update_algorithms.py
lion/utils/__init__.py
lion/utils/costs.py
lion/utils/general.py
lion/utils/ksp.py
lion/utils/plotting.py
lion/utils/shortest_path.py
lion_sp-0.1.1.dist-info/LICENSE
lion_sp-0.1.1.dist-info/METADATA
lion_sp-0.1.1.dist-info/WHEEL
lion_sp-0.1.1.dist-info/top_level.txt
lion_sp-0.1.1.dist-info/RECORD
