Metadata-Version: 2.1
Name: lion-sp
Version: 0.1.1
Summary: LInear Optimization Networks - shortest path algorithms
Home-page: https://github.com/NinaWie/lion
Author: Nina Wiedemann
Author-email: nwiedemann@uos.de
License: GPLv3
Platform: UNKNOWN
Classifier: License :: OSI Approved :: GNU General Public License v3 (GPLv3)
Classifier: Intended Audience :: Science/Research
Classifier: Programming Language :: Python :: 3.6
Classifier: Topic :: Software Development :: Libraries :: Python Modules
Requires-Python: >=3.6
Requires-Dist: numpy
Requires-Dist: numba
Requires-Dist: scipy
Requires-Dist: coverage
